csv_ical/__init__.py
csv_ical/__version__.py
csv_ical/convert.py
csv_ical/py.typed
csv_ical/tests/__init__.py
csv_ical/tests/test_convert.py
csv_ical/tests/test_version.py
csv_ical-2.2.0.dist-info/METADATA
csv_ical-2.2.0.dist-info/WHEEL
csv_ical-2.2.0.dist-info/top_level.txt
csv_ical-2.2.0.dist-info/RECORD
